{
  "costco": { "domains": ["costco.com"], "wikipedia": "Costco" },
  "sam's club": { "domains": ["samsclub.com"], "wikipedia": "Sam's_Club" },
  "sams club": { "domains": ["samsclub.com"] },
  "kroger": { "domains": ["kroger.com"], "wikipedia": "Kroger" },
  "albertsons": { "domains": ["albertsons.com"], "wikipedia": "Albertsons" },
  "publix": { "domains": ["publix.com"], "wikipedia": "Publix" },
  "whole foods": { "domains": ["wholefoodsmarket.com"], "wikipedia": "Whole_Foods_Market" },
  "trader joe's": { "domains": ["traderjoes.com"], "wikipedia": "Trader_Joe's" },
  "trader joes": { "domains": ["traderjoes.com"] },
  "aldi": { "domains": ["aldi.com"], "wikipedia": "Aldi" },
  "lidl": { "domains": ["lidl.com"], "wikipedia": "Lidl" },
  "carrefour": { "domains": ["carrefour.com"], "wikipedia": "Carrefour" },
  "tesco": { "domains": ["tesco.com"], "wikipedia": "Tesco" },
  "sainsbury's": { "domains": ["sainsburys.co.uk"], "wikipedia": "Sainsbury's" },
  "sainsburys": { "domains": ["sainsburys.co.uk"] },
  "asda": { "domains": ["asda.com"], "wikipedia": "Asda" },
  "morrisons": { "domains": ["morrisons.com"], "wikipedia": "Morrisons" },
  "waitrose": { "domains": ["waitrose.com"], "wikipedia": "Waitrose" },
  "co-op": { "domains": ["coop.co.uk"], "wikipedia": "The_Co-operative_Group" },
  "auchan": { "domains": ["auchan.com"], "wikipedia": "Auchan" },
  "e.leclerc": { "domains": ["e.leclerc"], "clearbitDomains": ["e.leclerc"], "wikipedia": "E.Leclerc" },
  "intermarche": { "domains": ["intermarche.com"], "wikipedia": "Intermarché" },
  "rewe": { "domains": ["rewe.de"], "wikipedia": "REWE_Group" },
  "edeka": { "domains": ["edeka.de"], "wikipedia": "Edeka" },
  "kaufland": { "domains": ["kaufland.de"], "wikipedia": "Kaufland" },
  "albert heijn": { "domains": ["ah.nl"], "wikipedia": "Albert_Heijn" },
  "jumbo": { "domains": ["jumbo.com"], "wikipedia": "Jumbo_(supermarket)" },
  "hema": { "domains": ["hema.com"], "wikipedia": "HEMA_(store)" },
  "blokker": { "domains": ["blokker.nl"], "wikipedia": "Blokker_(company)" },
  "kruidvat": { "domains": ["kruidvat.nl"], "wikipedia": "Kruidvat" },
  "etos": { "domains": ["etos.nl"], "wikipedia": "Etos" },
  "miniso": { "domains": ["miniso.com"], "wikipedia": "Miniso" },
  "名创优品": { "domains": ["miniso.com"], "wikipedia": "Miniso" },
  "watsons": { "domains": ["watsons.com"], "wikipedia": "Watsons" },
  "屈臣氏": { "domains": ["watsons.com"], "wikipedia": "Watsons" },
  "uniqlo": { "domains": ["uniqlo.com"], "wikipedia": "Uniqlo" },
  "优衣库": { "domains": ["uniqlo.com"], "wikipedia": "Uniqlo" },
  "muji": { "domains": ["muji.com"], "wikipedia": "Muji" },
  "无印良品": { "domains": ["muji.com"], "wikipedia": "Muji" },
  "ikea": { "domains": ["ikea.com"], "wikipedia": "IKEA" },
  "hay": { "domains": ["hay.dk"], "wikipedia": "HAY_(company)" },
  "normann copenhagen": { "domains": ["normann-copenhagen.com"] },
  "muuto": { "domains": ["muuto.com"] },
  "menu": { "domains": ["menu.as"] },
  "gubi": { "domains": ["gubi.com"] },
  "tradition": { "domains": ["andtradition.com"] },
  "ferm living": { "domains": ["fermliving.com"] },
  "vitra": { "domains": ["vitra.com"], "wikipedia": "Vitra_(furniture)" },
  "knoll": { "domains": ["knoll.com"], "wikipedia": "Knoll_(company)" },
  "herman miller": { "domains": ["hermanmiller.com"], "wikipedia": "Herman_Miller" },
  "steelcase": { "domains": ["steelcase.com"], "wikipedia": "Steelcase" },
  "rakuten": { "domains": ["rakuten.com"], "wikipedia": "Rakuten" },
  "楽天": { "domains": ["rakuten.com"], "wikipedia": "Rakuten" },
  "tmall": { "domains": ["tmall.com"], "wikipedia": "Tmall" },
  "天猫": { "domains": ["tmall.com"], "wikipedia": "Tmall" },
  "jd.com": { "domains": ["jd.com"], "wikipedia": "JD.com" },
  "京东": { "domains": ["jd.com"], "wikipedia": "JD.com" },
  "taobao": { "domains": ["taobao.com"], "wikipedia": "Taobao" },
  "淘宝": { "domains": ["taobao.com"], "wikipedia": "Taobao" },
  "pinduoduo": { "domains": ["pinduoduo.com"], "wikipedia": "Pinduoduo" },
  "拼多多": { "domains": ["pinduoduo.com"], "wikipedia": "Pinduoduo" },
  "vipshop": { "domains": ["vipshop.com"], "wikipedia": "Vipshop" },
  "唯品会": { "domains": ["vipshop.com"], "wikipedia": "Vipshop" },
  "xiaohongshu": { "domains": ["xiaohongshu.com"], "wikipedia": "Xiaohongshu" },
  "小红书": { "domains": ["xiaohongshu.com"], "wikipedia": "Xiaohongshu" },
  "suning": { "domains": ["suning.com"], "wikipedia": "Suning.com" },
  "苏宁易购": { "domains": ["suning.com"], "wikipedia": "Suning.com" },
  "kaola": { "domains": ["kaola.com"] },
  "网易考拉": { "domains": ["kaola.com"] },
  "netease yanxuan": { "domains": ["you.163.com"], "clearbitDomains": ["163.com"], "wikipedia": "NetEase" },
  "网易严选": { "domains": ["you.163.com"], "clearbitDomains": ["163.com"] },
  "xiaomi youpin": { "domains": ["youpin.mi.com"], "clearbitDomains": ["mi.com"] },
  "小米有品": { "domains": ["youpin.mi.com"], "clearbitDomains": ["mi.com"] },
  "meilishuo": { "domains": ["meilishuo.com"] },
  "美丽说": { "domains": ["meilishuo.com"] },
  "mogujie": { "domains": ["mogujie.com"], "wikipedia": "Mogujie" },
  "蘑菇街": { "domains": ["mogujie.com"], "wikipedia": "Mogujie" },
  "dangdang": { "domains": ["dangdang.com"], "wikipedia": "Dangdang" },
  "当当": { "domains": ["dangdang.com"], "wikipedia": "Dangdang" },
  "gome": { "domains": ["gome.com.cn"], "clearbitDomains": ["gome.com.cn"], "wikipedia": "GOME_Electrical_Appliances" },
  "国美": { "domains": ["gome.com.cn"], "clearbitDomains": ["gome.com.cn"], "wikipedia": "GOME_Electrical_Appliances" },
  "costco": { "domains": ["costco.com"], "wikipedia": "Costco" },
  "amazon": { "domains": ["amazon.com"], "wikipedia": "Amazon_(company)" },
  "ebay": { "domains": ["ebay.com"], "wikipedia": "EBay" },
  "etsy": { "domains": ["etsy.com"], "wikipedia": "Etsy" },
  "wayfair": { "domains": ["wayfair.com"], "wikipedia": "Wayfair" },
  "best buy": { "domains": ["bestbuy.com"], "wikipedia": "Best_Buy" },
  "home depot": { "domains": ["homedepot.com"], "wikipedia": "The_Home_Depot" },
  "lowe's": { "domains": ["lowes.com"], "wikipedia": "Lowe's" },
  "lowes": { "domains": ["lowes.com"] },
  "menards": { "domains": ["menards.com"], "wikipedia": "Menards" },
  "ikea": { "domains": ["ikea.com"], "wikipedia": "IKEA" }
}
